egnn_jax/__init__.py
egnn_jax/egnn.py
egnn_jax/utils.py
egnn_jax/variants.py
egnn_jax-0.3.dist-info/LICENSE
egnn_jax-0.3.dist-info/METADATA
egnn_jax-0.3.dist-info/WHEEL
egnn_jax-0.3.dist-info/top_level.txt
egnn_jax-0.3.dist-info/RECORD
