Metadata-Version: 2.1
Name: egnn-jax
Version: 0.3
Summary: E(3) GNN in jax
Author: Gianluca Galletti
Author-email: g.galletti@tum.de
Classifier: Programming Language :: Python :: 3.8
Requires-Python: >=3.8
License-File: LICENSE
Requires-Dist: dm-haiku (==0.0.9)
Requires-Dist: jax (==0.4.10)
Requires-Dist: jaxlib (==0.4.10)
Requires-Dist: jraph (==0.0.6.dev0)
Requires-Dist: numpy (>=1.23.4)
Requires-Dist: optax (==0.1.3)
